{
    "header": {
        "id": "cf604c77-2f9b-40dd-9a65-3c00928ff69b",
        "creation_date_time": "2023-06-15T14:09:01.650Z",
        "acquisition_provenance": {
            "source_name": "Google Fit API",
            "source_origin_id": "raw:com.google.step_count.cumulative:Xiaomi:M2103K19G:76151d60:STEP_COUNTER"
        },
        "schema_id": {
            "namespace": "omh",
            "name": "speed",
            "version": "1.0"
        }
    },
    "body": {
        "effective_time_frame": {
            "date_time": "2023-06-15T10:48:50.386774569Z"
        },
        "speed": {
            "unit": "m/s",
            "value": 0.8993974801277795
        }
    }
}